quickeeg/__init__.py
quickeeg/quickeeg_main.py
quickeeg/data/.gitignore
quickeeg/helpers/preprocessing.py
quickeeg/helpers/report.py
quickeeg/helpers/simulate.py
quickeeg/plots/.gitignore
quickeeg/reports/.gitignore
quickeeg/tests/__init__.py
quickeeg/tests/test_preprocessing.py
quickeeg/tests/test_simulate.py
quickeeg-0.0.14.dist-info/METADATA
quickeeg-0.0.14.dist-info/WHEEL
quickeeg-0.0.14.dist-info/licenses/LICENSE
quickeeg-0.0.14.dist-info/RECORD
