Metadata-Version: 2.4
Name: quickeeg
Version: 0.0.14
Summary: This package provides a quick and easy pipeline to process EEG files and generate a report. It is a wrapper for mne.
Project-URL: Homepage, https://github.com/chadcwilliams/quickeeg
Project-URL: Repository, https://github.com/chadcwilliams/quickeeg
Author-email: Chad Williams <chadwilliams.ccw@gmail.com>
License-File: LICENSE
Requires-Python: >=3.7
Requires-Dist: markdown-pdf~=1.3
Requires-Dist: matplotlib~=3.9
Requires-Dist: mne~=1.8
Requires-Dist: numpy~=2.1
Requires-Dist: scikit-learn~=1.5
